MANIFEST.in
README.md
setup.py
django_icetea.egg-info/PKG-INFO
django_icetea.egg-info/SOURCES.txt
django_icetea.egg-info/dependency_links.txt
django_icetea.egg-info/not-zip-safe
django_icetea.egg-info/requires.txt
django_icetea.egg-info/top_level.txt
icetea/__init__.py
icetea/authentication.py
icetea/custom_filters.py
icetea/emitters.py
icetea/exceptions.py
icetea/handlers.py
icetea/resource.py
icetea/tests.py
icetea/utils.py