Metadata-Version: 1.0
Name: django-icetea
Version: 0.5
Summary: REST API Framework
Home-page: http://github.com/stargazer/django-icetea
Author: C. Paschalides
Author-email: already.late@gmail.com
License: WTFPL
Keywords: rest,restful,api,crud
Platform: UNKNOWN
Classifier: Programming Language :: Python
Classifier: Operating System :: OS Independent
Classifier: Topic :: Internet :: WWW/HTTP
Classifier: Framework :: Django
Classifier: Intended Audience :: Developers
Classifier: License :: Freely Distributable
Classifier: Development Status :: 4 - Beta
